LICENSE
MANIFEST.in
README.md
setup.py
exoatlas/__init__.py
exoatlas/imports.py
exoatlas/version.py
exoatlas.egg-info/PKG-INFO
exoatlas.egg-info/SOURCES.txt
exoatlas.egg-info/dependency_links.txt
exoatlas.egg-info/not-zip-safe
exoatlas.egg-info/requires.txt
exoatlas.egg-info/top_level.txt
exoatlas/models/__init__.py
exoatlas/models/chen.py
exoatlas/models/kopparapu.py
exoatlas/models/seager.py
exoatlas/models/zeng.py
exoatlas/models/data/README.txt
exoatlas/models/data/seager/README.txt
exoatlas/models/data/seager/gj1214mr_hhe.txt
exoatlas/models/data/seager/gj1214mr_rock.txt
exoatlas/models/data/zengandsasselov/README.txt
exoatlas/populations/__init__.py
exoatlas/populations/collections.py
exoatlas/populations/downloader.py
exoatlas/populations/pineda_skew.py
exoatlas/populations/population_core.py
exoatlas/populations/predefined.py
exoatlas/populations/summary.py
exoatlas/populations/calculations/__init__.py
exoatlas/populations/calculations/observability.py
exoatlas/populations/calculations/planetary.py
exoatlas/populations/calculations/planning.py
exoatlas/populations/calculations/stellar.py
exoatlas/populations/data/README.txt
exoatlas/populations/data/__init__.py
exoatlas/populations/data/skewnormal_parameters_for_interpolating_mode.ecsv
exoatlas/populations/data/solarsystem/README.txt
exoatlas/populations/data/solarsystem/__init__.py
exoatlas/populations/data/solarsystem/jpl-ssd-dwarf-planets.txt
exoatlas/populations/data/solarsystem/jpl-ssd-moons.txt
exoatlas/populations/data/solarsystem/jpl-ssd-planets.txt
exoatlas/populations/data/solarsystem/solarsystem.txt
exoatlas/populations/exoplanets/__init__.py
exoatlas/populations/exoplanets/exoplanet_archive_comparisons.py
exoatlas/populations/exoplanets/exoplanet_downloaders.py
exoatlas/populations/exoplanets/exoplanets.py
exoatlas/populations/exoplanets/transiting_exoplanets.py
exoatlas/populations/exoplanets/transiting_exoplanets_subsets.py
exoatlas/populations/solarsystem/__init__.py
exoatlas/populations/solarsystem/minorplanets.py
exoatlas/populations/solarsystem/moons.py
exoatlas/populations/solarsystem/planets.py
exoatlas/populations/solarsystem/sbdb_downloader.py
